QuickSQL3/__init__.py
QuickSQL3/sql.py
QuickSQL3/sql_async.py
quicksql3-0.1.4.dist-info/LICENSE
quicksql3-0.1.4.dist-info/METADATA
quicksql3-0.1.4.dist-info/WHEEL
quicksql3-0.1.4.dist-info/top_level.txt
quicksql3-0.1.4.dist-info/RECORD
