Metadata-Version: 2.2
Name: QuickSQL3
Version: 0.1.4
Summary: A simple library for working with SQLite3 databases.
Home-page: https://github.com/JustDev-oper/QuickSQL3/
Author: Arthur
Author-email: itoppro11@gmail.com
Classifier: Programming Language :: Python :: 3
Classifier: License :: OSI Approved :: MIT License
Classifier: Operating System :: OS Independent
Requires-Python: >=3.6
License-File: LICENSE
Requires-Dist: aiosqlite>=0.17.0
Dynamic: author
Dynamic: author-email
Dynamic: classifier
Dynamic: description
Dynamic: description-content-type
Dynamic: home-page
Dynamic: requires-dist
Dynamic: requires-python
Dynamic: summary
